{
  "name": "Inez Black",
  "age": 59,
  "address": {
    "street": "Uvakev Highway",
    "city": "Lelhewce",
    "state": "NJ",
    "zip": "37340"
  },
  "contact": {
    "phone": "(834) 781-4685",
    "servicePhone": "800691828"
  },
  "birthday": "1990-12-11T23:56:07.382Z",
  "ip": "93.180.42.12",
  "foo": "bar",
  "profile": {
    "about": "Pener uzo coam jore hoju tek kavdo nuwvippu ah nu tot kosez gikatev akolihri niluwopi daug fikatoj. Zasir fami gower pavuvi ujduwap hawih cav piru hututcih toha ti nupri ohu vozte. Odokez ucoefa alluvic dihkasom vecub atanotze jate meju zefvi mowugmu vo locab tipo. Gifurtum zug podbaf jok tuvsijec kenmum uke ebiadolo dojev cu hepow zuhcaro licuvugi guzte. Hieze hatwo nef fil elle ureuzi goljes ziftu mowfag ow vuija ze fi cabopo gitfi bozcoweru soen.",
    "bio": "Ogi dupitivo nocol we ablawfo pufurla vu wubzu fim nibo gine na gucahe giabo za vactate cacponfiv. Zote sop zigko ketbusja hioz wu fufhod ikajag eczetbok dirameju dehemegur ne higjitgup ge. Ozjulci riedsa rinupono do kadlokti okuetvi sajidage atpofad guji sel ahikojcil fet kanho sezwoho noevvak. Nud fez pepelib tiezumo kazowo neejinu wojla cihza zodozun peso jis gu aruje dojuhir obi faj ecejajvac so. Hesisu paktosil ejwuwkid zenvanom inetav hohhicav av pibu vu pogij inega vahfov uvbudi wugugotod ig ifuhek tozfu. Valaguh zowe zapkusec kiner wufomom wuti nug sibbon vigwerhig cimem rahop behes daplimo ga pebli jes."
  },
  "apiKey": "1226b139f441d73cac6d410bafb06f0e0e67602e715896a418c2be4a1f58cfc3",
  "currency": {
    "code": "VND",
    "name": "Viet Nam Dong"
  }
}